README.md
setup.py
ddgz/main.py
ddgz.egg-info/PKG-INFO
ddgz.egg-info/SOURCES.txt
ddgz.egg-info/dependency_links.txt
ddgz.egg-info/entry_points.txt
ddgz.egg-info/requires.txt
ddgz.egg-info/top_level.txt