Metadata-Version: 2.1
Name: ddgz
Version: 1.0.0
Summary: Search with duckduckgo from the command-line, fuzzy select the results.
Home-page: https://github.com/talwrii/ddgz
Author: talwrii
Author-email: talwrii@gmail.com
License: MIT
Keywords: duckduckgo,search
